red_teaming/__init__.py
red_teaming-0.0.1.dist-info/METADATA
red_teaming-0.0.1.dist-info/WHEEL
red_teaming-0.0.1.dist-info/RECORD
