Metadata-Version: 2.4
Name: red-teaming
Version: 0.0.1
Summary: Whitecircle.ai red teaming helpers for probing LLM weaknesses safely.
Author: White Circle
License: MIT
Keywords: ai,red teaming,security,testing,whitecircle.ai
Classifier: Development Status :: 3 - Alpha
Classifier: License :: OSI Approved :: MIT License
Classifier: Programming Language :: Python :: 3
Requires-Python: >=3.9
